airbyte_cdk/__init__.py
airbyte_cdk/connector.py
airbyte_cdk/entrypoint.py
airbyte_cdk/logger.py
airbyte_cdk/destinations/__init__.py
airbyte_cdk/destinations/destination.py
airbyte_cdk/models/__init__.py
airbyte_cdk/models/airbyte_protocol.py
airbyte_cdk/sources/__init__.py
airbyte_cdk/sources/abstract_source.py
airbyte_cdk/sources/source.py
airbyte_cdk/sources/deprecated/__init__.py
airbyte_cdk/sources/deprecated/base_source.py
airbyte_cdk/sources/deprecated/client.py
airbyte_cdk/sources/singer/__init__.py
airbyte_cdk/sources/singer/singer_helpers.py
airbyte_cdk/sources/singer/source.py
airbyte_cdk/sources/streams/__init__.py
airbyte_cdk/sources/streams/core.py
airbyte_cdk/sources/streams/http/__init__.py
airbyte_cdk/sources/streams/http/exceptions.py
airbyte_cdk/sources/streams/http/http.py
airbyte_cdk/sources/streams/http/rate_limiting.py
airbyte_cdk/sources/streams/http/auth/__init__.py
airbyte_cdk/sources/streams/http/auth/core.py
airbyte_cdk/sources/streams/http/auth/oauth.py
airbyte_cdk/sources/streams/http/auth/token.py
airbyte_cdk/sources/streams/http/requests_native_auth/__init__.py
airbyte_cdk/sources/streams/http/requests_native_auth/oauth.py
airbyte_cdk/sources/streams/http/requests_native_auth/token.py
airbyte_cdk/sources/utils/__init__.py
airbyte_cdk/sources/utils/casing.py
airbyte_cdk/sources/utils/catalog_helpers.py
airbyte_cdk/sources/utils/schema_helpers.py
airbyte_cdk/sources/utils/transform.py
unit_tests/destinations/__init__.py
unit_tests/destinations/test_destination.py
unit_tests/singer/__init__.py
unit_tests/singer/test_singer_helpers.py
unit_tests/singer/test_singer_source.py
unit_tests/sources/__init__.py
unit_tests/sources/test_abstract_source.py
unit_tests/sources/test_source.py
unit_tests/sources/streams/__init__.py
unit_tests/sources/streams/test_streams_core.py
unit_tests/sources/streams/http/__init__.py
unit_tests/sources/streams/http/test_http.py
unit_tests/sources/streams/http/auth/__init__.py
airbyte_cdk_velocity-0.1.32.dist-info/LICENSE.txt
airbyte_cdk_velocity-0.1.32.dist-info/METADATA
airbyte_cdk_velocity-0.1.32.dist-info/WHEEL
airbyte_cdk_velocity-0.1.32.dist-info/entry_points.txt
airbyte_cdk_velocity-0.1.32.dist-info/top_level.txt
airbyte_cdk_velocity-0.1.32.dist-info/RECORD
